LICENSE.txt
MANIFEST.in
README.rst
setup.cfg
setup.py
sphinxcontrib/__init__.py
sphinxcontrib/microdata.py
sphinxcontrib/tests.py
sphinxcontrib/test-resources/microdata_itemprop.rst
sphinxcontrib/test-resources/microdata_itemprop_url.rst
sphinxcontrib/test-resources/microdata_itemscope.rst
sphinxcontrib/test-resources/microdata_itemscope_nested.rst
sphinxcontrib/test-resources/microdata_itemscope_nested_compact.rst
sphinxcontrib/test-resources/microdata_itemscope_tag.rst
sphinxcontrib_microdata.egg-info/PKG-INFO
sphinxcontrib_microdata.egg-info/SOURCES.txt
sphinxcontrib_microdata.egg-info/dependency_links.txt
sphinxcontrib_microdata.egg-info/namespace_packages.txt
sphinxcontrib_microdata.egg-info/not-zip-safe
sphinxcontrib_microdata.egg-info/requires.txt
sphinxcontrib_microdata.egg-info/top_level.txt