Metadata-Version: 1.1
Name: sphinxcontrib-microdata
Version: 0.1dev-20140921
Summary: Sphinx "microdata" extension
Home-page: http://bitbucket.org/birkenfeld/sphinx-contrib
Author: Fabrice Salvaire
Author-email: fabrice.salvaire@orange.fr
License: LGPL v3
Download-URL: http://pypi.python.org/pypi/sphinxcontrib-microdata
Platform: any
Classifier: Development Status :: 4 - Beta
Classifier: Environment :: Console
Classifier: Environment :: Web Environment
Classifier: Intended Audience :: Developers
Classifier: License :: OSI Approved :: BSD License
Classifier: Operating System :: OS Independent
Classifier: Programming Language :: Python
Classifier: Topic :: Documentation
Classifier: Topic :: Utilities
